app.py
my_cloud_devops_consulting-5.18.9.dist-info/METADATA
my_cloud_devops_consulting-5.18.9.dist-info/WHEEL
my_cloud_devops_consulting-5.18.9.dist-info/top_level.txt
my_cloud_devops_consulting-5.18.9.dist-info/RECORD
