Metadata-Version: 2.4
Name: my-cloud-devops-consulting
Version: 5.18.9
Summary: This is my consulting website for Cloud & DevOps services.
Home-page: https://github.com/Betrand1999/project-root
Author: Betrand Mutagha
Author-email: mmutagha@gmail.com
Classifier: Programming Language :: Python :: 3
Classifier: Programming Language :: Python :: 3.10
Classifier: License :: OSI Approved :: MIT License
Classifier: Operating System :: OS Independent
Requires-Python: >=3.6
Requires-Dist: Flask>=2.0
Requires-Dist: pymongo
Requires-Dist: werkzeug
Requires-Dist: requests
Dynamic: author
Dynamic: author-email
Dynamic: classifier
Dynamic: description
Dynamic: description-content-type
Dynamic: home-page
Dynamic: requires-dist
Dynamic: requires-python
Dynamic: summary
